MANIFEST.in
requirements.txt
setup.py
ml_metrics/__init__.py
ml_metrics/auc.py
ml_metrics/average_precision.py
ml_metrics/edit_distance.py
ml_metrics/elementwise.py
ml_metrics/quadratic_weighted_kappa.py
ml_metrics.egg-info/PKG-INFO
ml_metrics.egg-info/SOURCES.txt
ml_metrics.egg-info/dependency_links.txt
ml_metrics.egg-info/requires.txt
ml_metrics.egg-info/top_level.txt
ml_metrics/custom/__init__.py
ml_metrics/custom/binomial_deviance.py
ml_metrics/custom/kdd_average_precision.py