Metadata-Version: 1.0
Name: ml_metrics
Version: 0.1.4
Summary: Machine Learning Evaluation Metrics
Home-page: UNKNOWN
Author: Ben Hamner
Author-email: ben@benhamner.com
License: UNKNOWN
Platform: UNKNOWN
